auth_proxy_jwt/__init__.py
auth_proxy_jwt/plugin.py
auth_proxy_jwt-0.2.0.dist-info/METADATA
auth_proxy_jwt-0.2.0.dist-info/WHEEL
auth_proxy_jwt-0.2.0.dist-info/entry_points.txt
auth_proxy_jwt-0.2.0.dist-info/licenses/LICENSE
auth_proxy_jwt-0.2.0.dist-info/RECORD
