Metadata-Version: 2.4
Name: auth-proxy-jwt
Version: 0.2.0
Summary: JWT authentication plugin for python-auth-proxy
Project-URL: Homepage, https://git.private.coffee/kumi/auth-proxy-jwt
Project-URL: Bug Tracker, https://git.private.coffee/kumi/auth-proxy-jwt/issues
Author-email: Kumi Mitterer <auth-proxy@kumi.email>
License: MIT
License-File: LICENSE
Classifier: Development Status :: 4 - Beta
Classifier: Intended Audience :: System Administrators
Classifier: License :: OSI Approved :: MIT License
Classifier: Programming Language :: Python :: 3
Classifier: Programming Language :: Python :: 3.8
Classifier: Programming Language :: Python :: 3.9
Classifier: Programming Language :: Python :: 3.10
Classifier: Programming Language :: Python :: 3.11
Classifier: Programming Language :: Python :: 3.12
Classifier: Programming Language :: Python :: 3.13
Classifier: Topic :: Internet :: WWW/HTTP :: HTTP Servers
Classifier: Topic :: Security
Requires-Python: >=3.8
Requires-Dist: pyjwt
Requires-Dist: python-auth-proxy>=0.2.0
